matrix42sdk/AuthNClient.py
matrix42sdk/Exceptions.py
matrix42sdk/__init__.py
matrix42sdk/api_endpoints/__init__.py
matrix42sdk/api_endpoints/fragments.py
matrix42sdk/api_endpoints/objects.py
matrix42sdk-3.0.3.dist-info/LICENSE
matrix42sdk-3.0.3.dist-info/METADATA
matrix42sdk-3.0.3.dist-info/WHEEL
matrix42sdk-3.0.3.dist-info/RECORD
