Metadata-Version: 2.1
Name: matrix42sdk
Version: 3.0.3
Summary: Python SDK for Matrix42 Enterprise Service Management CMBD
Home-page: https://github.com/dmpe/matrix42sdk
License: MIT
Author: John Malc
Author-email: cincenko@outlook.com
Requires-Python: >=3.8,<4.0
Classifier: Development Status :: 5 - Production/Stable
Classifier: Intended Audience :: Developers
Classifier: License :: OSI Approved :: MIT License
Classifier: Operating System :: OS Independent
Classifier: Programming Language :: Python :: 3
Classifier: Programming Language :: Python :: 3.8
Classifier: Programming Language :: Python :: 3.9
Classifier: Programming Language :: Python :: 3.10
Classifier: Programming Language :: Python :: 3.11
Classifier: Programming Language :: Python :: 3.12
Classifier: Topic :: Internet :: WWW/HTTP
Classifier: Topic :: Software Development :: Libraries :: Python Modules
Requires-Dist: mypy
Requires-Dist: requests
Project-URL: Documentation, https://github.com/dmpe/matrix42sdk
